README.rst
setup.py
clearbit/__init__.py
clearbit/discovery.py
clearbit/error.py
clearbit/prospector.py
clearbit/resource.py
clearbit/reveal.py
clearbit/risk.py
clearbit/tests.py
clearbit/version.py
clearbit/watchlist.py
clearbit.egg-info/PKG-INFO
clearbit.egg-info/SOURCES.txt
clearbit.egg-info/dependency_links.txt
clearbit.egg-info/requires.txt
clearbit.egg-info/top_level.txt
clearbit/../VERSION
clearbit/enrichment/__init__.py
clearbit/enrichment/company.py
clearbit/enrichment/person.py
clearbit/enrichment/person_company.py